jenkins_autojobs/__init__.py
jenkins_autojobs/git.py
jenkins_autojobs/hg.py
jenkins_autojobs/hg_remote_helper.py
jenkins_autojobs/job.py
jenkins_autojobs/main.py
jenkins_autojobs/python26_support.py
jenkins_autojobs/svn.py
jenkins_autojobs/util.py
jenkins_autojobs/utils.py
jenkins_autojobs/version.py
jenkins_autojobs-0.17.4.dist-info/DESCRIPTION.rst
jenkins_autojobs-0.17.4.dist-info/METADATA
jenkins_autojobs-0.17.4.dist-info/RECORD
jenkins_autojobs-0.17.4.dist-info/WHEEL
jenkins_autojobs-0.17.4.dist-info/entry_points.txt
jenkins_autojobs-0.17.4.dist-info/metadata.json
jenkins_autojobs-0.17.4.dist-info/top_level.txt
